{
  "dependencies": [
    {
      "name": "constructs",
      "version": "^10.0.0",
      "type": "build"
    },
    {
      "name": "esbuild",
      "type": "build"
    },
    {
      "name": "jest",
      "type": "build"
    },
    {
      "name": "jest-junit",
      "version": "^15",
      "type": "build"
    },
    {
      "name": "projen",
      "type": "build"
    },
    {
      "name": "tesseractocr",
      "type": "runtime"
    }
  ],
  "//": "~~ Generated by projen. To modify, edit .projenrc.js and run \"npx projen\"."
}
